pep249.py
pep249-1.1.0.dist-info/LICENSE
pep249-1.1.0.dist-info/METADATA
pep249-1.1.0.dist-info/WHEEL
pep249-1.1.0.dist-info/top_level.txt
pep249-1.1.0.dist-info/RECORD
