Metadata-Version: 2.1
Name: pep249
Version: 1.1.0
Summary: Provide minimum implementation check and connection pool of PEP249.
Home-page: https://github.com/abersheeran/pep249
Author: abersheeran
Author-email: me@abersheeran.com
License: MIT
Platform: UNKNOWN
Classifier: License :: OSI Approved :: MIT License
Classifier: Programming Language :: Python
Classifier: Programming Language :: Python :: Implementation :: CPython
Classifier: Programming Language :: Python :: Implementation :: PyPy
Requires-Python: >=3.7.0
License-File: LICENSE
